repl_session/__init__.py
repl_session/py.typed
repl_session-0.1.0.dist-info/licenses/LICENSE
repl_session-0.1.0.dist-info/METADATA
repl_session-0.1.0.dist-info/WHEEL
repl_session-0.1.0.dist-info/entry_points.txt
repl_session-0.1.0.dist-info/top_level.txt
repl_session-0.1.0.dist-info/RECORD
