Metadata-Version: 2.4
Name: repl-session
Version: 0.1.0
Summary: Runs a session with a Read-Eval-Print-Loop (REPL). Takes YAML as input gives JSON as output.
Classifier: Development Status :: 3 - Alpha
Classifier: Environment :: Console
Classifier: Intended Audience :: Developers
Classifier: License :: OSI Approved :: Apache Software License
Classifier: Topic :: Software Development
Classifier: Topic :: Utilities
Requires-Python: >=3.11
License-File: LICENSE
Requires-Dist: argh>=0.30.5
Requires-Dist: msgspec>=0.19.0
Requires-Dist: pexpect>=4.9.0
Dynamic: license-file
